resklogits/__init__.py
resklogits/cache.py
resklogits/cli.py
resklogits/config_parser.py
resklogits/pattern_automata.py
resklogits/py.typed
resklogits/rule_engine.py
resklogits/rule_templates.py
resklogits/shadow_ban_processor.py
resklogits/vectorized_aho_corasick.py
resklogits/data/banned_phrases.json
resklogits-0.1.2.dist-info/METADATA
resklogits-0.1.2.dist-info/WHEEL
resklogits-0.1.2.dist-info/entry_points.txt
resklogits-0.1.2.dist-info/licenses/LICENSE
resklogits-0.1.2.dist-info/RECORD
