Metadata-Version: 2.4
Name: resklogits
Version: 0.1.2
Summary: ReskLogits shadow ban logits processor for LLM safety filtering
Project-URL: Homepage, https://github.com/Resk-Security/resk-logits
Project-URL: Repository, https://github.com/Resk-Security/resk-logits
Project-URL: Issues, https://github.com/Resk-Security/resk-logits/issues
Author: RESK Team
License: APACHE 2
License-File: LICENSE
Keywords: aho-corasick,filtering,gpu,llm,logits,safety,transformers
Classifier: Development Status :: 4 - Beta
Classifier: Intended Audience :: Developers
Classifier: Intended Audience :: Science/Research
Classifier: License :: OSI Approved :: MIT License
Classifier: Programming Language :: Python :: 3
Classifier: Programming Language :: Python :: 3.13
Classifier: Topic :: Scientific/Engineering :: Artificial Intelligence
Classifier: Topic :: Software Development :: Libraries :: Python Modules
Requires-Python: >=3.13
Requires-Dist: pyyaml>=6.0
Requires-Dist: torch>=2.0.0
Requires-Dist: transformers>=4.35.0
Provides-Extra: accelerate
Requires-Dist: accelerate>=0.24.0; extra == 'accelerate'
Provides-Extra: dev
Requires-Dist: accelerate>=0.24.0; extra == 'dev'
Requires-Dist: black>=23.0.0; extra == 'dev'
Requires-Dist: mypy>=1.0.0; extra == 'dev'
Requires-Dist: pytest>=7.0.0; extra == 'dev'
Requires-Dist: ruff>=0.1.0; extra == 'dev'
Requires-Dist: types-pyyaml>=6.0; extra == 'dev'
